odoo/addons/sale_stock_release_channel_partner_by_date_delivery/README.rst
odoo/addons/sale_stock_release_channel_partner_by_date_delivery/__init__.py
odoo/addons/sale_stock_release_channel_partner_by_date_delivery/__manifest__.py
odoo/addons/sale_stock_release_channel_partner_by_date_delivery/i18n/it.po
odoo/addons/sale_stock_release_channel_partner_by_date_delivery/i18n/sale_stock_release_channel_partner_by_date_delivery.pot
odoo/addons/sale_stock_release_channel_partner_by_date_delivery/models/__init__.py
odoo/addons/sale_stock_release_channel_partner_by_date_delivery/models/sale_order.py
odoo/addons/sale_stock_release_channel_partner_by_date_delivery/readme/CONTRIBUTORS.rst
odoo/addons/sale_stock_release_channel_partner_by_date_delivery/readme/DESCRIPTION.rst
odoo/addons/sale_stock_release_channel_partner_by_date_delivery/static/description/icon.png
odoo/addons/sale_stock_release_channel_partner_by_date_delivery/static/description/index.html
odoo/addons/sale_stock_release_channel_partner_by_date_delivery/tests/__init__.py
odoo/addons/sale_stock_release_channel_partner_by_date_delivery/tests/test_sale_release_channel.py
odoo/addons/sale_stock_release_channel_partner_by_date_delivery/views/sale_order.xml
odoo_addon_sale_stock_release_channel_partner_by_date_delivery-16.0.1.1.1.dist-info/METADATA
odoo_addon_sale_stock_release_channel_partner_by_date_delivery-16.0.1.1.1.dist-info/WHEEL
odoo_addon_sale_stock_release_channel_partner_by_date_delivery-16.0.1.1.1.dist-info/top_level.txt
odoo_addon_sale_stock_release_channel_partner_by_date_delivery-16.0.1.1.1.dist-info/RECORD
