Metadata-Version: 2.1
Name: odoo-addon-sale_stock_release_channel_partner_by_date_delivery
Version: 16.0.1.1.1
Summary: Filters channels on sales based on selected carrier.
Home-page: https://github.com/OCA/wms
Author: Camptocamp, BCIM, Odoo Community Association (OCA)
Author-email: support@odoo-community.org
License: AGPL-3
Classifier: Programming Language :: Python
Classifier: Framework :: Odoo
Classifier: Framework :: Odoo :: 16.0
Classifier: License :: OSI Approved :: GNU Affero General Public License v3
Classifier: Development Status :: 4 - Beta
Requires-Python: >=3.10
Requires-Dist: odoo-addon-sale-stock-release-channel-partner-by-date<16.1dev,>=16.0dev
Requires-Dist: odoo-addon-stock-release-channel-delivery<16.1dev,>=16.0dev
Requires-Dist: odoo<16.1dev,>=16.0a
